{"dealId":"164","freq":80,"hand":"md|4S92HKJ7532DAJ8CKT,SAQT853H4DQ75C842,SHA986D9643CAQJ97,SKJ764HQTDKT2C653|sv|N|ah|Board+2|mb|P|mb|1H|mb|2S|an|Aggressive+weak+jump+overcall+--+6++!S;+9-+HCP;+3++total+points|mb|3S|an|Cue+bid+--+3++!H;+13++total+points|mb|4S|an|The+Law:+10+trump+->+game+support+--+2++!S;+11-+HCP;+12-+total+points|mb|5H|an|5++!H;+11-21+HCP;+12-22+total+points|mb|P|mb|P|mb|P|pc|DQ|pc|D3|pc|DT|pc|DA|pc|H2|pc|H4|pc|HA|pc|HT|pc|H6|pc|HQ|pc|HK|pc|S8|pc|CK|pc|C2|pc|C7|pc|C3|pc|CT|pc|C4|pc|CA|pc|C6|pc|CQ|pc|C5|pc|D8|pc|C8|pc|CJ|pc|S4|pc|DJ|pc|S5|pc|C9|pc|S7|pc|S2|pc|S3|mc|13|","score":0.38,"scoreType":"IMP"}