{"dealId":"088","freq":37,"hand":"md|1SK2HJT5DAT965CK76,S987HAQ9763D8CA42,SAQJT43H8DQJ7CJT9,S65HK42DK432CQ853|sv|E|ah|Board+3|mb|1D|an|Minor+suit+opening+--+3++!D;+11-21+HCP;+12-22+total+points|mb|2H|an|Aggressive+weak+jump+overcall+--+6++!H;+10-+HCP;+3++total+points|mb|2S|an|Free+bid+--+5++!S;+11++total+points;+forcing|mb|3H|an|The+Law:+9+trump+->+3+level+--+2++!H;+4-21+total+points|mb|P|mb|P|mb|3S|an|6++!S;+11-12+total+points|mb|P|mb|P|mb|P|pc|H2|pc|HT|pc|HA|pc|H8|pc|D8|pc|DJ|pc|D4|pc|D5|pc|S3|pc|S6|pc|SK|pc|S7|pc|S2|pc|S9|pc|SA|pc|S5|pc|SQ|pc|H4|pc|H5|pc|S8|pc|DQ|pc|D3|pc|D6|pc|H3|pc|D7|pc|D2|pc|D9|pc|C2|pc|DA|pc|H9|pc|C9|pc|DK|pc|DT|pc|H7|pc|CT|pc|C8|pc|HJ|pc|H6|pc|S4|pc|HK|pc|CJ|pc|CQ|pc|CK|pc|CA|pc|C4|pc|ST|pc|C5|pc|C6|pc|SJ|pc|C3|pc|C7|pc|HQ|","score":-1.16,"scoreType":"IMP"}