{"dealId":"481","freq":40,"hand":"md|1S962HJ6DAK7CAKT74,SKT53HA9DJ9852C32,SQ4HKQT543DQ63C65,SAJ87H872DT4CQJ98|sv|E|ah|Board+3|mb|1N|an|notrump+opener.+Could+have+5M.+--+2-5+!C;+2-5+!D;+2-5+!H;+2-5+!S;+15-17+HCP;+18-+total+points|mb|P|mb|4D!|an|Texas+--+6++!H;+10++total+points|mb|P|mb|4H|an|2-5+!C;+2-5+!D;+2-5+!H;+2-5+!S;+15-17+HCP;+18-+total+points|mb|P|mb|P|mb|P|pc|D5|pc|D6|pc|DT|pc|DA|pc|H6|pc|HA|pc|H3|pc|H7|pc|D2|pc|D3|pc|D4|pc|D7|pc|HJ|pc|H9|pc|HK|pc|H2|pc|HQ|pc|H8|pc|S2|pc|ST|pc|C5|pc|CJ|pc|CA|pc|C3|pc|CK|pc|C2|pc|C6|pc|C8|pc|C4|pc|S5|pc|H4|pc|C9|pc|DQ|pc|S8|pc|DK|pc|DJ|pc|CT|pc|S3|pc|S4|pc|CQ|pc|S7|pc|S6|pc|SK|pc|SQ|pc|D9|pc|H5|pc|SA|pc|C7|pc|HT|pc|SJ|pc|S9|pc|D8|","score":2.36,"scoreType":"IMP"}